{"1": ["31hfdi3q2fmzrfwvosyha34d66ke", "Admin", "hbplaymaker@gmail.com", "bossbaby"], "2": [null, "test2@email.com", "2345", "2@gmail.com"], "3": [null, "test3@email.com", "3456", "3@gmail.com"], "4": [null, "test4@email.com", "4567", "4@gmail.com"], "5": [null, "test5@email.com", "5678", "5@gmail.com"], "6": [null, "test6@email.com", "6789", "6@gmail.com"], "7": [null, "test7@email.com", "78910", "7@gmail.com"], "8": [null, "test8@email.com", "891011", "8@gmail.com"], "9": [null, "test9@email.com", "9101112", "9@gmail.com"], "10": [null, "test10@email.com", "10111213", "10@gmail.com"], "11": [null, "test11@email.com", "11121314", "11@gmail.com"], "12": [null, "test12@email.com", "12131415", "12@gmail.com"], "13": [null, "test13@email.com", "13141516", "13@gmail.com"], "14": [null, "test14@email.com", "14151617", "14@gmail.com"], "15": [null, "test15@email.com", "15161718", "15@gmail.com"], "16": [null, "test16@email.com", "16171819", "16@gmail.com"], "17": [null, "test17@email.com", "17181920", "17@gmail.com"], "18": [null, "test18@email.com", "18192021", "18@gmail.com"], "19": [null, "test19@email.com", "19202122", "19@gmail.com"], "20": ["1232430322", "The Boss", "kayejrosen@gmail.com", "mommy"]}